djson_form/__init__.py
djson_form/admin.py
djson_form/apps.py
djson_form/forms.py
djson_form/models.py
djson_form/tests.py
djson_form/views.py
djson_form/migrations/0001_initial.py
djson_form/migrations/__init__.py
djson_form/templates/admin/json_schema_form.html
djson_form/utils/__init__.py
djson_form/utils/cast.py
djson_form/utils/fields.py
djson_form/utils/submit.py
djson_form-1.0.6.dist-info/licenses/LICENSE
djson_form-1.0.6.dist-info/METADATA
djson_form-1.0.6.dist-info/WHEEL
djson_form-1.0.6.dist-info/top_level.txt
djson_form-1.0.6.dist-info/RECORD
