Metadata-Version: 2.4
Name: djson-form
Version: 1.0.6
Summary: Add your description here
Requires-Python: >=3.12
License-File: LICENSE
Requires-Dist: django>=4.2
Dynamic: license-file
